pswrd_entropy_gen/__init__.py
pswrd_entropy_gen/generator.py
pswrd_entropy_gen-2.0.0.dist-info/licenses/LICENSE.txt
pswrd_entropy_gen-2.0.0.dist-info/METADATA
pswrd_entropy_gen-2.0.0.dist-info/WHEEL
pswrd_entropy_gen-2.0.0.dist-info/top_level.txt
pswrd_entropy_gen-2.0.0.dist-info/RECORD
