Metadata-Version: 2.4
Name: pswrd_entropy_gen
Version: 2.0.0
Summary: Password generator based on entropy
Author-email: Alfredo Tzintzun <alfredotzintzun4@gmail.com>
License: MIT License
Project-URL: Homepage, https://github.com/Tzintzun444/pswrd_entropy_gen
Project-URL: Issues, https://github.com/Tzintzun444/pswrd_entropy_gen#readme
Keywords: password,entropy,generator,cibersecurity,cryptography
Classifier: Programming Language :: Python :: 3
Classifier: License :: OSI Approved :: MIT License
Classifier: Operating System :: OS Independent
Requires-Python: >=3.10
License-File: LICENSE.txt
Dynamic: license-file
